{
  "-39838": {
    "IsKinematic": false,
    "UseGravity": true,
    "Constraints": 0,
    "Mass": 1.0
  },
  "-39818": {
    "IsKinematic": false,
    "UseGravity": true,
    "Constraints": 0,
    "Mass": 1.0
  },
  "-39798": {
    "IsKinematic": false,
    "UseGravity": true,
    "Constraints": 0,
    "Mass": 1.0
  },
  "-39778": {
    "IsKinematic": false,
    "UseGravity": true,
    "Constraints": 0,
    "Mass": 1.0
  },
  "-39572": {
    "IsKinematic": false,
    "UseGravity": true,
    "Constraints": 0,
    "Mass": 1.0
  },
  "-39552": {
    "IsKinematic": false,
    "UseGravity": true,
    "Constraints": 0,
    "Mass": 1.0
  },
  "-39532": {
    "IsKinematic": false,
    "UseGravity": true,
    "Constraints": 0,
    "Mass": 1.0
  },
  "-39476": {
    "IsKinematic": false,
    "UseGravity": true,
    "Constraints": 0,
    "Mass": 1.0
  },
  "-39496": {
    "IsKinematic": false,
    "UseGravity": true,
    "Constraints": 0,
    "Mass": 1.0
  },
  "-39592": {
    "IsKinematic": false,
    "UseGravity": true,
    "Constraints": 0,
    "Mass": 1.0
  },
  "-39858": {
    "IsKinematic": false,
    "UseGravity": true,
    "Constraints": 0,
    "Mass": 1.0
  },
  "-44628": {
    "IsKinematic": false,
    "UseGravity": true,
    "Constraints": 0,
    "Mass": 1.0
  },
  "-44648": {
    "IsKinematic": false,
    "UseGravity": true,
    "Constraints": 0,
    "Mass": 1.0
  }
}